quicklearnkit/__init__.py
quicklearnkit/classifier.py
quicklearnkit/plotting.py
quicklearnkit/quickimports.py
quicklearnkit/randomizer.py
quicklearnkit/regressor.py
quicklearnkit/split.py
quicklearnkit/utils.py
quicklearnkit-0.3.2.dist-info/licenses/LICENSE
quicklearnkit-0.3.2.dist-info/METADATA
quicklearnkit-0.3.2.dist-info/WHEEL
quicklearnkit-0.3.2.dist-info/top_level.txt
quicklearnkit-0.3.2.dist-info/RECORD
