Metadata-Version: 2.4
Name: quicklearnkit
Version: 0.3.2
Summary: Learning-first machine learning utilities library for simplified imports, sampling, splitting, and probabilistic preprocessing.
Author: Hazi Afrid
License: MIT License
Requires-Python: >=3.8
License-File: LICENSE
Requires-Dist: numpy
Requires-Dist: pandas
Requires-Dist: scikit-learn
Requires-Dist: xgboost
Requires-Dist: seaborn
Requires-Dist: matplotlib
Dynamic: license-file
